rask_njord_riak
