Metadata-Version: 1.0
Name: rask-njord-riak
Version: 0.0.11
Summary: Rask Riak Connector
Home-page: https://gitlab.com/vikingmakt/rask_njord_riak
Author: Umgeher Torgersen
Author-email: me@umgeher.org
License: https://gitlab.com/vikingmakt/rask_njord_riak/raw/master/LICENSE
Platform: UNKNOWN
